<InterfaceSummary>
<RtlPorts>
<name>A_stim_reset</name>
<CType>
<TypeName>short</TypeName>
<TypeWidth>16</TypeWidth>
<PhysicalWidth>16</PhysicalWidth>
</CType>
<CFractionWidth>0</CFractionWidth>
<InvalidType>0</InvalidType>
</RtlPorts>
<RtlPorts>
<name>V_stim_reset</name>
<CType>
<TypeName>short</TypeName>
<TypeWidth>16</TypeWidth>
<PhysicalWidth>16</PhysicalWidth>
</CType>
<CFractionWidth>0</CFractionWidth>
<InvalidType>0</InvalidType>
</RtlPorts>
<RtlPorts>
<name>set_thresh</name>
<CType>
<TypeName>short</TypeName>
<TypeWidth>16</TypeWidth>
<PhysicalWidth>16</PhysicalWidth>
</CType>
<CFractionWidth>0</CFractionWidth>
<InvalidType>0</InvalidType>
</RtlPorts>
<RtlPorts>
<name>v_thresh</name>
<CType>
<TypeName>int</TypeName>
<TypeWidth>32</TypeWidth>
<PhysicalWidth>32</PhysicalWidth>
</CType>
<CFractionWidth>0</CFractionWidth>
<InvalidType>0</InvalidType>
</RtlPorts>
<RtlPorts>
<name>a_thresh</name>
<CType>
<TypeName>int</TypeName>
<TypeWidth>32</TypeWidth>
<PhysicalWidth>32</PhysicalWidth>
</CType>
<CFractionWidth>0</CFractionWidth>
<InvalidType>0</InvalidType>
</RtlPorts>
<RtlPorts>
<name>a_flip</name>
<CType>
<TypeName>int</TypeName>
<TypeWidth>32</TypeWidth>
<PhysicalWidth>32</PhysicalWidth>
</CType>
<CFractionWidth>0</CFractionWidth>
<InvalidType>0</InvalidType>
</RtlPorts>
<RtlPorts>
<name>v_flip</name>
<CType>
<TypeName>int</TypeName>
<TypeWidth>32</TypeWidth>
<PhysicalWidth>32</PhysicalWidth>
</CType>
<CFractionWidth>0</CFractionWidth>
<InvalidType>0</InvalidType>
</RtlPorts>
<RtlPorts>
<name>datapoint</name>
<CType>
<TypeName>short</TypeName>
<TypeWidth>16</TypeWidth>
<PhysicalWidth>16</PhysicalWidth>
</CType>
<CFractionWidth>0</CFractionWidth>
<InvalidType>0</InvalidType>
</RtlPorts>
<RtlPorts>
<name>out_r</name>
<CType>
<TypeName>short</TypeName>
<TypeWidth>16</TypeWidth>
<PhysicalWidth>16</PhysicalWidth>
</CType>
<CFractionWidth>0</CFractionWidth>
<InvalidType>0</InvalidType>
</RtlPorts>
<RtlPorts>
<name>stim</name>
<CType>
<TypeName>short</TypeName>
<TypeWidth>16</TypeWidth>
<PhysicalWidth>16</PhysicalWidth>
</CType>
<CFractionWidth>0</CFractionWidth>
<InvalidType>0</InvalidType>
</RtlPorts>
</InterfaceSummary>

